emoji_logger/__init__.py
emoji_logger/main.py
emoji_logger-0.1.17.dist-info/METADATA
emoji_logger-0.1.17.dist-info/WHEEL
emoji_logger-0.1.17.dist-info/licenses/LICENSE
emoji_logger-0.1.17.dist-info/RECORD
