Metadata-Version: 2.4
Name: emoji_logger
Version: 0.1.17
Summary: Custom python logging module
Author-email: KyungHo Kim <qqaa3030@gmail.com>
License: MIT
License-File: LICENSE
Requires-Python: >=3.9
